django_hellwebprice_events/__init__.py
django_hellwebprice_events/apps.py
django_hellwebprice_events/conf.py
django_hellwebprice_events/consumer.py
django_hellwebprice_events/event_manager.py
django_hellwebprice_events/generics.py
django_hellwebprice_events/routes.py
django_hellwebprice_events/tests.py
pip/__init__.py
pip/__main__.py
pip/_internal/__init__.py
pip/_internal/build_env.py
pip/_internal/cache.py
pip/_internal/configuration.py
pip/_internal/exceptions.py
pip/_internal/locations.py
pip/_internal/main.py
pip/_internal/pyproject.py
pip/_internal/self_outdated_check.py
pip/_internal/wheel_builder.py
pip/_internal/cli/__init__.py
pip/_internal/cli/autocompletion.py
pip/_internal/cli/base_command.py
pip/_internal/cli/cmdoptions.py
pip/_internal/cli/command_context.py
pip/_internal/cli/main.py
pip/_internal/cli/main_parser.py
pip/_internal/cli/parser.py
pip/_internal/cli/progress_bars.py
pip/_internal/cli/req_command.py
pip/_internal/cli/spinners.py
pip/_internal/cli/status_codes.py
pip/_internal/commands/__init__.py
pip/_internal/commands/cache.py
pip/_internal/commands/check.py
pip/_internal/commands/completion.py
pip/_internal/commands/configuration.py
pip/_internal/commands/debug.py
pip/_internal/commands/download.py
pip/_internal/commands/freeze.py
pip/_internal/commands/hash.py
pip/_internal/commands/help.py
pip/_internal/commands/install.py
pip/_internal/commands/list.py
pip/_internal/commands/search.py
pip/_internal/commands/show.py
pip/_internal/commands/uninstall.py
pip/_internal/commands/wheel.py
pip/_internal/distributions/__init__.py
pip/_internal/distributions/base.py
pip/_internal/distributions/installed.py
pip/_internal/distributions/sdist.py
pip/_internal/distributions/wheel.py
pip/_internal/index/__init__.py
pip/_internal/index/collector.py
pip/_internal/index/package_finder.py
pip/_internal/models/__init__.py
pip/_internal/models/candidate.py
pip/_internal/models/direct_url.py
pip/_internal/models/format_control.py
channels_hellwebprice_events-1.0.0.dist-info/METADATA
channels_hellwebprice_events-1.0.0.dist-info/WHEEL
channels_hellwebprice_events-1.0.0.dist-info/top_level.txt
channels_hellwebprice_events-1.0.0.dist-info/RECORD
